{
  "schema": "omd.live-inspect-proof.v1",
  "brand": "gmarket",
  "captured_at": "2026-05-15",
  "method": "Chrome DevTools Protocol :9222 / Runtime.evaluate / getComputedStyle",
  "browser": "Chrome/148.0.7778.97",
  "surfaces": [
    {
      "url": "https://www.gmarket.co.kr/",
      "title": "G마켓 - 지금부터의 마켓",
      "sample_count": 182,
      "css_var_count": 247
    },
    {
      "url": "https://www.gmarket.co.kr/n/best",
      "title": "G마켓 - G마켓 베스트>전체",
      "sample_count": 90,
      "css_var_count": 246
    }
  ],
  "raw_samples": [
    {
      "tag": "SPAN",
      "text": "쿠폰적용가",
      "cls": "text__price-title",
      "bg": "rgba(0, 0, 0, 0)",
      "color": "rgb(218, 18, 13)",
      "radius": "0px",
      "border": "0px none rgb(218, 18, 13)",
      "padding": "0px 2px 0px 0px",
      "h": 11,
      "w": 55,
      "fontSize": "11px",
      "fontWeight": "500",
      "fontFamily": "\"Gmarket Sans\", sans-serif",
      "lineHeight": "14px",
      "boxShadow": "none",
      "textDecoration": "none"
    },
    {
      "tag": "A",
      "text": "검색창 바로가기",
      "cls": "",
      "bg": "rgb(17, 121, 234)",
      "color": "rgb(255, 255, 255)",
      "radius": "0px",
      "border": "0px none rgb(255, 255, 255)",
      "padding": "9px 0px",
      "h": 18,
      "w": 1265,
      "fontSize": "0px",
      "fontWeight": "400",
      "fontFamily": "-apple-system, \"system-ui\", \"Apple SD Gothic Neo\", Roboto, \"Noto Sans CJK KR\", Tahoma, \"Noto Sans KR\", \"Gmarket Sans\", sans-serif",
      "lineHeight": "0px",
      "boxShadow": "none",
      "textDecoration": "none"
    },
    {
      "tag": "H1",
      "text": "G마켓",
      "cls": "box__title-logo",
      "bg": "rgba(0, 0, 0, 0)",
      "color": "rgb(0, 0, 0)",
      "radius": "0px",
      "border": "0px none rgb(0, 0, 0)",
      "padding": "0px",
      "h": 113,
      "w": 240,
      "fontSize": "0px",
      "fontWeight": "700",
      "fontFamily": "-apple-system, \"system-ui\", \"Apple SD Gothic Neo\", Roboto, \"Noto Sans CJK KR\", Tahoma, \"Noto Sans KR\", \"Gmarket Sans\", sans-serif",
      "lineHeight": "normal",
      "boxShadow": "none",
      "textDecoration": "none"
    },
    {
      "tag": "BUTTON",
      "text": "",
      "cls": "button__search general-clk-spm-d",
      "bg": "rgba(0, 0, 0, 0)",
      "color": "rgb(0, 0, 0)",
      "radius": "0px",
      "border": "0px none rgb(0, 0, 0)",
      "padding": "5px",
      "h": 32,
      "w": 32,
      "fontSize": "13.3333px",
      "fontWeight": "400",
      "fontFamily": "-apple-system, \"system-ui\", \"Apple SD Gothic Neo\", Roboto, \"Noto Sans CJK KR\", Tahoma, \"Noto Sans KR\", \"Gmarket Sans\", sans-serif",
      "lineHeight": "normal",
      "boxShadow": "none",
      "textDecoration": "none"
    },
    {
      "tag": "BUTTON",
      "text": "",
      "cls": "button",
      "bg": "rgba(0, 0, 0, 0)",
      "color": "rgb(0, 0, 0)",
      "radius": "0px",
      "border": "0px none rgb(0, 0, 0)",
      "padding": "0px",
      "h": 80,
      "w": 74,
      "fontSize": "13.3333px",
      "fontWeight": "400",
      "fontFamily": "-apple-system, \"system-ui\", \"Apple SD Gothic Neo\", Roboto, \"Noto Sans CJK KR\", Tahoma, \"Noto Sans KR\", \"Gmarket Sans\", sans-serif",
      "lineHeight": "normal",
      "boxShadow": "none",
      "textDecoration": "none"
    },
    {
      "tag": "A",
      "text": "하나더",
      "cls": "link__tab",
      "bg": "rgba(0, 0, 0, 0)",
      "color": "rgb(102, 102, 102)",
      "radius": "20px",
      "border": "0px none rgb(102, 102, 102)",
      "padding": "0px",
      "h": 40,
      "w": 134,
      "fontSize": "16px",
      "fontWeight": "400",
      "fontFamily": "-apple-system, \"system-ui\", \"Apple SD Gothic Neo\", Roboto, \"Noto Sans CJK KR\", Tahoma, \"Noto Sans KR\", \"Gmarket Sans\", sans-serif",
      "lineHeight": "40px",
      "boxShadow": "none",
      "textDecoration": "none"
    },
    {
      "tag": "H2",
      "text": "G마켓 베스트",
      "cls": "text__title",
      "bg": "rgba(0, 0, 0, 0)",
      "color": "rgb(0, 0, 0)",
      "radius": "0px",
      "border": "0px none rgb(0, 0, 0)",
      "padding": "0px",
      "h": 32,
      "w": 169,
      "fontSize": "28px",
      "fontWeight": "400",
      "fontFamily": "\"Gmarket Sans\", sans-serif",
      "lineHeight": "32px",
      "boxShadow": "none",
      "textDecoration": "none"
    },
    {
      "tag": "SPAN",
      "text": "52%",
      "cls": "text text__value",
      "bg": "rgba(0, 0, 0, 0)",
      "color": "rgb(218, 18, 13)",
      "radius": "0px",
      "border": "0px none rgb(218, 18, 13)",
      "padding": "0px",
      "h": 12,
      "w": 27,
      "fontSize": "12px",
      "fontWeight": "400",
      "fontFamily": "\"Gmarket Sans\", sans-serif",
      "lineHeight": "16px",
      "boxShadow": "none",
      "textDecoration": "none"
    }
  ],
  "top_observed_colors_home": {
    "rgb(0, 0, 0)": 65,
    "rgb(255, 255, 255)": 22,
    "rgb(0, 0, 238)": 21,
    "rgb(34, 34, 34)": 18,
    "rgb(218, 18, 13)": 11,
    "rgb(66, 66, 66)": 8,
    "rgb(148, 152, 159)": 6,
    "rgb(94, 99, 109)": 5,
    "rgb(119, 119, 119)": 4,
    "rgb(158, 158, 158)": 4,
    "rgb(153, 153, 153)": 3,
    "rgb(97, 97, 97)": 3
  },
  "top_observed_radii_home": {
    "4px 0px": 5,
    "10px": 3,
    "20px": 3,
    "27px": 2,
    "24px": 1,
    "6px": 1,
    "50%": 1,
    "6px 0px 0px 6px": 1
  },
  "css_var_groups_home": {
    "Gray": 10,
    "Red": 10,
    "Orange": 10,
    "Yellow": 10,
    "Green": 11,
    "Teal": 10,
    "Blue": 10,
    "Indigo": 10,
    "Purple": 10,
    "Pink": 10,
    "Club": 15,
    "Event": 3,
    "Smile-Yellow": 1,
    "StarDelivery-Purple": 1,
    "Green-Connect-Blue": 1,
    "gmarketFont": 1,
    "Font": 1,
    "minWidth": 1
  },
  "ip_guardrails": {
    "logo": "reference only — not redistributed",
    "taglines": "no verbatim Gmarket taglines reproduced; '지금부터의 마켓' referenced once as factual positioning evidence in §11 narrative",
    "tokens": "factual CSS custom-property values reproduced under analytical fair-use",
    "fonts": "Gmarket Sans is SIL OFL — free to redistribute; download URL referenced, file not vendored"
  }
}